validation_report/__init__.py
validation_report/apps.py
validation_report/sendmail.py
validation_report/urls.py
validation_report/utils.py
validation_report/validation_report.py
validation_report/views.py
validation_report/management/__init__.py
validation_report/management/commands/__init__.py
validation_report/management/commands/validationreport.py
django_validation_report-1.0.3.dist-info/LICENSE
django_validation_report-1.0.3.dist-info/METADATA
django_validation_report-1.0.3.dist-info/WHEEL
django_validation_report-1.0.3.dist-info/top_level.txt
django_validation_report-1.0.3.dist-info/RECORD
